setup.cfg
setup.py
settings_resolver/__init__.py
settings_resolver/main.py
settings_resolver/merged_tree.py
settings_resolver.egg-info/PKG-INFO
settings_resolver.egg-info/SOURCES.txt
settings_resolver.egg-info/dependency_links.txt
settings_resolver.egg-info/requires.txt
settings_resolver.egg-info/top_level.txt
test/test_merge.py
test/test_sd.py