Metadata-Version: 1.1
Name: settings-resolver
Version: 1.0.4
Summary: Allows interdependent Django settings overrides, through late binding
Home-page: https://github.com/klortho/settings-resolver
Author: Chris Maloney
Author-email: voldrani@gmail.com
License: WTFPL
Platform: UNKNOWN
Classifier: Intended Audience :: Developers
Classifier: Operating System :: OS Independent
Classifier: Programming Language :: Python :: 2
Classifier: Programming Language :: Python :: 3
